LICENSE
MANIFEST.in
README.rst
setup.py
django_code_linter.egg-info/PKG-INFO
django_code_linter.egg-info/SOURCES.txt
django_code_linter.egg-info/dependency_links.txt
django_code_linter.egg-info/entry_points.txt
django_code_linter.egg-info/top_level.txt
djinter/__init__.py
djinter/__init__.pyc
djinter/lint.py
djinter/lint.pyc
djinter/main.py
djinter/main.pyc
djinter/utils.py
djinter/utils.pyc