Metadata-Version: 1.1
Name: django-code-linter
Version: 0.0.1
Summary: suite to test django code style
Home-page: https://github.com/42cc/django-code-linter
Author: 42 Coffee Cups
Author-email: contact@42cc.co
License: BSD License
Download-URL: https://github.com/42cc/django-code-linter/archive/master.zip
Keywords: ripple,api
Platform: UNKNOWN
Classifier: Environment :: Web Environment
Classifier: Intended Audience :: Developers
Classifier: License :: OSI Approved :: BSD License
Classifier: Programming Language :: Python
Requires: python (>= 2.7)
